afx/__init__.py
afx/exceptions.py
afx/globals.py
afx/models.py
afx/pypi/__init__.py
afx/pypi/indexes.py
afx/pypi/models.py
afx/table.py
afx/tenant.py
afx/terraform/__init__.py
afx/terraform/lambda_function.py
afx/terraform/models.py
afx/terraform/well_known.py
libafx-0.2.1.dist-info/METADATA
libafx-0.2.1.dist-info/WHEEL
libafx-0.2.1.dist-info/RECORD
